dewey/TrainingManager.py
dewey/cli.py
dewey/core.py
dewey/internal/PluginData.py
dewey/internal/PluginManager.py
dewey/plugins/base.py
dewey/plugins/pytorch.py
dewey/plugins/pytorch_checkpoints.py
dewey/plugins/pytorch_tensorboard.py
dewey/plugins/tensorflow.py
dewey/plugins/tensorflow_checkpoints.py
dewey/plugins/training_progress.py
pydewey-0.3.3.data/scripts/dwy
pydewey-0.3.3.data/scripts/dwy.bat
pydewey-0.3.3.dist-info/METADATA
pydewey-0.3.3.dist-info/WHEEL
pydewey-0.3.3.dist-info/namespace_packages.txt
pydewey-0.3.3.dist-info/top_level.txt
pydewey-0.3.3.dist-info/zip-safe
pydewey-0.3.3.dist-info/RECORD
